{
  "npcId": 2092,
  "talks": [
    {
      "id": 6209201,
      "beginWay": "TALK_BEGIN_MANUAL",
      "priority": 3,
      "nextTalks": [
        6209202,
        6209203
      ],
      "initDialog": 620920101,
      "npcId": [
        2092
      ],
      "assetIndex": 156918327881
    },
    {
      "id": 6209202,
      "beginWay": "TALK_BEGIN_MANUAL",
      "priority": 1,
      "initDialog": 620920201,
      "npcId": [
        2092
      ],
      "assetIndex": 1066933987548
    },
    {
      "id": 6209203,
      "beginWay": "TALK_BEGIN_MANUAL",
      "priority": 1,
      "initDialog": 620920301,
      "npcId": [
        2092
      ],
      "assetIndex": 617595823846
    },
    {
      "id": 7209201,
      "beginWay": "TALK_BEGIN_MANUAL",
      "beginCond": [
        {
          "type": "QUEST_COND_ACTIVITY_OPEN",
          "param": [
            "1001",
            "",
            ""
          ]
        }
      ],
      "priority": 4,
      "nextTalks": [
        7209202,
        7209203
      ],
      "initDialog": 720920101,
      "npcId": [
        2092
      ],
      "assetIndex": 409226928904
    },
    {
      "id": 7209202,
      "beginWay": "TALK_BEGIN_MANUAL",
      "priority": 1,
      "initDialog": 720920201,
      "npcId": [
        2092
      ],
      "assetIndex": 298688667504
    },
    {
      "id": 7209203,
      "beginWay": "TALK_BEGIN_MANUAL",
      "priority": 1,
      "initDialog": 720920301,
      "npcId": [
        2092
      ],
      "assetIndex": 209260740791
    }
  ]
}