{
  "$type": "ConfigInterContainer",
  "luaDataPath": "",
  "isSimpleTalk": false,
  "dontUseDefaultFinish": true,
  "pauseActor": false,
  "hidePickableEntity": false,
  "startBlackKeepTime": 0.0,
  "entityBan": "",
  "startFade": {
    "startFadeInDuration": 0.5,
    "startFadeOutDuration": 0.5
  },
  "endFade": {
    "startFadeInDuration": 0.0,
    "startFadeOutDuration": 0.0
  },
  "group": [
    [
      {
        "$type": "ConfigCameraMoveInterAction",
        "type": "CAMERA_MOVE",
        "delayTime": 0.0,
        "aliasList": [
          ""
        ],
        "duration": 1.0,
        "checkNextImmediately": false,
        "cameraPosType": "ABSOLUTE",
        "camPosOffset": {
          "x": -511.7566,
          "y": 211.278946,
          "z": 242.0189
        },
        "camForwardTargetOffset": {
          "x": -512.1498,
          "y": 210.8871,
          "z": 241.187119
        },
        "nearLength": 0.0,
        "camTargetType": "ABSOLUTE",
        "needElev": false,
        "camFov": 30.0,
        "camDutch": 0.0,
        "lerpRatio": 0.0,
        "lerpPattern": 6,
        "cameraBlendType": "EaseInOutCubic",
        "storyDither": false,
        "cutFrameTrans": {
          "enable": false,
          "duration": 1.0
        }
      },
      {
        "$type": "ConfigCameraMoveInterAction",
        "type": "CAMERA_MOVE",
        "delayTime": 0.1,
        "aliasList": [
          ""
        ],
        "duration": 2.0,
        "checkNextImmediately": false,
        "cameraPosType": "ABSOLUTE",
        "camPosOffset": {
          "x": -510.2648,
          "y": 210.20224,
          "z": 241.98674
        },
        "camForwardTargetOffset": {
          "x": -510.839874,
          "y": 209.981445,
          "z": 241.19899
        },
        "nearLength": 0.0,
        "camTargetType": "ABSOLUTE",
        "needElev": false,
        "camFov": 30.0,
        "camDutch": 0.0,
        "lerpRatio": 0.0,
        "lerpPattern": 0,
        "cameraBlendType": "EaseOutCubic",
        "storyDither": false,
        "cutFrameTrans": {
          "enable": false,
          "duration": 1.0
        }
      },
      {
        "$type": "ConfigMoveToAction",
        "type": "MOVE_TO",
        "delayTime": 0.0,
        "aliasList": [
          "Avatar"
        ],
        "duration": -1.0,
        "checkNextImmediately": false,
        "moveType": "NONE",
        "routeList": [
          {
            "x": -513.6391,
            "y": 207.806427,
            "z": 238.208969
          }
        ]
      },
      {
        "$type": "ConfigLookAtInterAction",
        "type": "LOOK_AT",
        "delayTime": 0.0,
        "aliasList": [
          "Avatar"
        ],
        "duration": -1.0,
        "checkNextImmediately": false,
        "enableHead": true,
        "useTargetPos": true,
        "enableAbsolute": true,
        "targetPosition": {
          "x": -513.621033,
          "y": 209.3011,
          "z": 236.8638
        },
        "targetOffset": {
          "x": 0.0,
          "y": 0.0,
          "z": 0.0
        },
        "headRotateVec": {
          "x": 0.0,
          "y": 0.0,
          "z": 0.0
        },
        "headTurnTime": 0.35,
        "enableBody": false,
        "bodyAngle": 0.0,
        "bodyTurnTime": 0.0
      },
      {
        "$type": "ConfigMoveToAction",
        "type": "MOVE_TO",
        "delayTime": 0.0,
        "aliasList": [
          "1005"
        ],
        "duration": -1.0,
        "checkNextImmediately": false,
        "moveType": "NONE",
        "routeList": [
          {
            "x": -512.622864,
            "y": 207.798843,
            "z": 237.348587
          }
        ]
      },
      {
        "$type": "ConfigLookAtInterAction",
        "type": "LOOK_AT",
        "delayTime": 0.0,
        "aliasList": [
          "1005"
        ],
        "duration": -1.0,
        "checkNextImmediately": false,
        "enableHead": true,
        "useTargetPos": true,
        "enableAbsolute": true,
        "targetPosition": {
          "x": -513.621033,
          "y": 209.3011,
          "z": 236.8638
        },
        "targetOffset": {
          "x": 0.0,
          "y": 0.0,
          "z": 0.0
        },
        "headRotateVec": {
          "x": 0.0,
          "y": 0.0,
          "z": 0.0
        },
        "headTurnTime": 0.35,
        "enableBody": false,
        "bodyAngle": 0.0,
        "bodyTurnTime": 0.0
      },
      {
        "$type": "ConfigBodyLangInterAction",
        "type": "BODY_LANG",
        "delayTime": 0.0,
        "aliasList": [
          "1005"
        ],
        "duration": -1.0,
        "checkNextImmediately": false,
        "bodyLangParam": 1090,
        "isContinue": false,
        "loopState": 0
      },
      {
        "$type": "ConfigSteerInterAction",
        "type": "STEER_TO",
        "delayTime": 0.0,
        "aliasList": [
          "1005"
        ],
        "duration": 1.0,
        "checkNextImmediately": false,
        "steerType": "FREE",
        "steerDir": {
          "x": -0.8995139,
          "y": 0.0,
          "z": -0.436892271
        },
        "useAngle": false,
        "steerAngle": 0.0,
        "useSteerAnim": false
      },
      {
        "$type": "ConfigMoveToAction",
        "type": "MOVE_TO",
        "delayTime": 0.0,
        "aliasList": [
          "10204"
        ],
        "duration": -1.0,
        "checkNextImmediately": false,
        "moveType": "NONE",
        "routeList": [
          {
            "x": -513.6728,
            "y": 207.919617,
            "z": 236.842239
          }
        ]
      },
      {
        "$type": "ConfigBodyLangInterAction",
        "type": "BODY_LANG",
        "delayTime": 0.0,
        "aliasList": [
          "10204"
        ],
        "duration": -1.0,
        "checkNextImmediately": false,
        "bodyLangParam": 1120,
        "isContinue": false,
        "loopState": 0
      },
      {
        "$type": "ConfigLookAtInterAction",
        "type": "LOOK_AT",
        "delayTime": 0.0,
        "aliasList": [
          "10204"
        ],
        "duration": -1.0,
        "checkNextImmediately": false,
        "enableHead": true,
        "useTargetPos": true,
        "enableAbsolute": true,
        "targetPosition": {
          "x": -513.6826,
          "y": 209.184,
          "z": 238.1666
        },
        "targetOffset": {
          "x": 0.0,
          "y": 0.0,
          "z": 0.0
        },
        "headRotateVec": {
          "x": 0.0,
          "y": 0.0,
          "z": 0.0
        },
        "headTurnTime": 0.35,
        "enableBody": false,
        "bodyAngle": 0.0,
        "bodyTurnTime": 0.0
      }
    ],
    [
      {
        "$type": "ConfigCameraMoveInterAction",
        "type": "CAMERA_MOVE",
        "delayTime": 0.0,
        "aliasList": [
          ""
        ],
        "duration": 1.0,
        "checkNextImmediately": false,
        "cameraPosType": "ABSOLUTE",
        "camPosOffset": {
          "x": -511.238251,
          "y": 209.2173,
          "z": 239.588333
        },
        "camForwardTargetOffset": {
          "x": -511.9075,
          "y": 209.082077,
          "z": 238.857712
        },
        "nearLength": 0.0,
        "camTargetType": "ABSOLUTE",
        "needElev": false,
        "camFov": 30.0,
        "camDutch": 0.0,
        "lerpRatio": 0.0,
        "lerpPattern": 6,
        "cameraBlendType": "EaseInOutCubic",
        "storyDither": false,
        "cutFrameTrans": {
          "enable": false,
          "duration": 1.0
        }
      },
      {
        "$type": "ConfigCameraMoveInterAction",
        "type": "CAMERA_MOVE",
        "delayTime": 0.1,
        "aliasList": [
          ""
        ],
        "duration": 20.0,
        "checkNextImmediately": false,
        "cameraPosType": "ABSOLUTE",
        "camPosOffset": {
          "x": -512.025146,
          "y": 209.157,
          "z": 240.172119
        },
        "camForwardTargetOffset": {
          "x": -512.4031,
          "y": 209.036652,
          "z": 239.25415
        },
        "nearLength": 0.0,
        "camTargetType": "ABSOLUTE",
        "needElev": false,
        "camFov": 30.0,
        "camDutch": 0.0,
        "lerpRatio": 0.0,
        "lerpPattern": 0,
        "cameraBlendType": "EaseInOutQuad",
        "storyDither": false,
        "cutFrameTrans": {
          "enable": false,
          "duration": 1.0
        }
      },
      {
        "$type": "ConfigDialogInterAction",
        "type": "DIALOG",
        "delayTime": 0.0,
        "aliasList": [
          "1005"
        ],
        "duration": -1.0,
        "checkNextImmediately": false,
        "dialogType": "LOCK_FRAME",
        "dialogID": 400030901,
        "protectTime": 0.0,
        "playAudio": true
      },
      {
        "$type": "ConfigEmoSyncInterAction",
        "type": "EMO_SYNC",
        "delayTime": 0.0,
        "aliasList": [
          "1005"
        ],
        "duration": -1.0,
        "checkNextImmediately": false,
        "dataPath": "Cs_Emo_Avatar_Simple_Common_Set/Cs_Emo_Avatar_Talk/Cs_Emo_Avatar_Event/Cs_Emo_Avatar_HaiDeng/Cs_Emo_400030901",
        "audioBankName": "",
        "audioName": "",
        "backType": "NONE",
        "enableBlink": true
      }
    ],
    [
      {
        "$type": "ConfigDialogInterAction",
        "type": "DIALOG",
        "delayTime": 0.0,
        "aliasList": [
          "10204"
        ],
        "duration": -1.0,
        "checkNextImmediately": false,
        "dialogType": "LOCK_FRAME",
        "dialogID": 400030902,
        "protectTime": 0.0,
        "playAudio": true
      },
      {
        "$type": "ConfigEmoSyncInterAction",
        "type": "EMO_SYNC",
        "delayTime": 0.0,
        "aliasList": [
          "10204"
        ],
        "duration": -1.0,
        "checkNextImmediately": false,
        "dataPath": "Cs_Emo_Avatar_Simple_Common_Set/Cs_Emo_Avatar_Talk/Cs_Emo_Avatar_Event/Cs_Emo_Avatar_HaiDeng/Cs_Emo_400030902",
        "audioBankName": "",
        "audioName": "",
        "backType": "NONE",
        "enableBlink": true
      }
    ],
    [
      {
        "$type": "ConfigLookAtInterAction",
        "type": "LOOK_AT",
        "delayTime": 0.305835515,
        "aliasList": [
          "Avatar"
        ],
        "duration": -1.0,
        "checkNextImmediately": false,
        "enableHead": true,
        "useTargetPos": true,
        "enableAbsolute": true,
        "targetPosition": {
          "x": -512.6313,
          "y": 209.1777,
          "z": 237.354019
        },
        "targetOffset": {
          "x": 0.0,
          "y": 0.0,
          "z": 0.0
        },
        "headRotateVec": {
          "x": 0.0,
          "y": 0.0,
          "z": 0.0
        },
        "headTurnTime": 0.35,
        "enableBody": false,
        "bodyAngle": 0.0,
        "bodyTurnTime": 0.0
      },
      {
        "$type": "ConfigDialogInterAction",
        "type": "DIALOG",
        "delayTime": 0.0,
        "aliasList": [
          "1005"
        ],
        "duration": -1.0,
        "checkNextImmediately": false,
        "dialogType": "LOCK_FRAME",
        "dialogID": 400030903,
        "protectTime": 0.5,
        "playAudio": true
      },
      {
        "$type": "ConfigBodyLangInterAction",
        "type": "BODY_LANG",
        "delayTime": 0.183333427,
        "aliasList": [
          "1005"
        ],
        "duration": -1.0,
        "checkNextImmediately": false,
        "bodyLangParam": 1120,
        "isContinue": false,
        "loopState": 0
      },
      {
        "$type": "ConfigSteerInterAction",
        "type": "STEER_TO",
        "delayTime": 0.0,
        "aliasList": [
          "1005"
        ],
        "duration": 1.0,
        "checkNextImmediately": false,
        "steerType": "FREE",
        "steerDir": {
          "x": -0.8396733,
          "y": 0.0,
          "z": 0.5430919
        },
        "useAngle": false,
        "steerAngle": 0.0,
        "useSteerAnim": false
      },
      {
        "$type": "ConfigLookAtInterAction",
        "type": "LOOK_AT",
        "delayTime": 0.0,
        "aliasList": [
          "1005"
        ],
        "duration": -1.0,
        "checkNextImmediately": false,
        "enableHead": true,
        "useTargetPos": true,
        "enableAbsolute": true,
        "targetPosition": {
          "x": -513.6826,
          "y": 209.184,
          "z": 238.1666
        },
        "targetOffset": {
          "x": 0.0,
          "y": 0.0,
          "z": 0.0
        },
        "headRotateVec": {
          "x": 0.0,
          "y": 0.0,
          "z": 0.0
        },
        "headTurnTime": 0.35,
        "enableBody": false,
        "bodyAngle": 0.0,
        "bodyTurnTime": 0.0
      },
      {
        "$type": "ConfigEmoSyncInterAction",
        "type": "EMO_SYNC",
        "delayTime": 0.0,
        "aliasList": [
          "1005"
        ],
        "duration": -1.0,
        "checkNextImmediately": false,
        "dataPath": "Cs_Emo_Avatar_Simple_Common_Set/Cs_Emo_Avatar_Talk/Cs_Emo_Avatar_Event/Cs_Emo_Avatar_HaiDeng/Cs_Emo_400030903",
        "audioBankName": "",
        "audioName": "",
        "backType": "NONE",
        "enableBlink": true
      },
      {
        "$type": "ConfigLookAtInterAction",
        "type": "LOOK_AT",
        "delayTime": 0.136944249,
        "aliasList": [
          "10204"
        ],
        "duration": -1.0,
        "checkNextImmediately": false,
        "enableHead": true,
        "useTargetPos": true,
        "enableAbsolute": true,
        "targetPosition": {
          "x": -512.6315,
          "y": 209.177734,
          "z": 237.343536
        },
        "targetOffset": {
          "x": 0.0,
          "y": 0.0,
          "z": 0.0
        },
        "headRotateVec": {
          "x": 0.0,
          "y": 0.0,
          "z": 0.0
        },
        "headTurnTime": 0.35,
        "enableBody": false,
        "bodyAngle": 0.0,
        "bodyTurnTime": 0.0
      }
    ],
    [
      {
        "$type": "ConfigDialogInterAction",
        "type": "DIALOG",
        "delayTime": 0.0,
        "aliasList": [
          "1005"
        ],
        "duration": -1.0,
        "checkNextImmediately": false,
        "dialogType": "LOCK_FRAME",
        "dialogID": 400030904,
        "protectTime": 0.466666728,
        "playAudio": true
      },
      {
        "$type": "ConfigSteerInterAction",
        "type": "STEER_TO",
        "delayTime": 0.0,
        "aliasList": [
          "1005"
        ],
        "duration": 1.0,
        "checkNextImmediately": false,
        "steerType": "FREE",
        "steerDir": {
          "x": -0.8995139,
          "y": 0.0,
          "z": -0.436892271
        },
        "useAngle": false,
        "steerAngle": 0.0,
        "useSteerAnim": false
      },
      {
        "$type": "ConfigLookAtInterAction",
        "type": "LOOK_AT",
        "delayTime": 0.0,
        "aliasList": [
          "1005"
        ],
        "duration": -1.0,
        "checkNextImmediately": false,
        "enableHead": true,
        "useTargetPos": true,
        "enableAbsolute": true,
        "targetPosition": {
          "x": -513.621033,
          "y": 209.3011,
          "z": 236.8638
        },
        "targetOffset": {
          "x": 0.0,
          "y": 0.0,
          "z": 0.0
        },
        "headRotateVec": {
          "x": 0.0,
          "y": 0.0,
          "z": 0.0
        },
        "headTurnTime": 0.35,
        "enableBody": false,
        "bodyAngle": 0.0,
        "bodyTurnTime": 0.0
      },
      {
        "$type": "ConfigBodyLangInterAction",
        "type": "BODY_LANG",
        "delayTime": 0.0,
        "aliasList": [
          "1005"
        ],
        "duration": -1.0,
        "checkNextImmediately": false,
        "bodyLangParam": 1040,
        "isContinue": false,
        "loopState": 0
      },
      {
        "$type": "ConfigEmoSyncInterAction",
        "type": "EMO_SYNC",
        "delayTime": 0.0,
        "aliasList": [
          "1005"
        ],
        "duration": -1.0,
        "checkNextImmediately": false,
        "dataPath": "Cs_Emo_Avatar_Simple_Common_Set/Cs_Emo_Avatar_Talk/Cs_Emo_Avatar_Event/Cs_Emo_Avatar_HaiDeng/Cs_Emo_400030904",
        "audioBankName": "",
        "audioName": "",
        "backType": "NONE",
        "enableBlink": true
      }
    ],
    [
      {
        "$type": "ConfigCameraMoveInterAction",
        "type": "CAMERA_MOVE",
        "delayTime": 0.0,
        "aliasList": [
          ""
        ],
        "duration": 1.5,
        "checkNextImmediately": false,
        "cameraPosType": "ABSOLUTE",
        "camPosOffset": {
          "x": -512.615967,
          "y": 209.15097,
          "z": 238.251709
        },
        "camForwardTargetOffset": {
          "x": -513.205566,
          "y": 209.147339,
          "z": 237.444031
        },
        "nearLength": 0.0,
        "camTargetType": "ABSOLUTE",
        "needElev": false,
        "camFov": 30.0,
        "camDutch": 0.0,
        "lerpRatio": 0.0,
        "lerpPattern": 6,
        "cameraBlendType": "EaseOutQuart",
        "storyDither": false,
        "cutFrameTrans": {
          "enable": false,
          "duration": 1.0
        }
      },
      {
        "$type": "ConfigCameraMoveInterAction",
        "type": "CAMERA_MOVE",
        "delayTime": 0.1,
        "aliasList": [
          ""
        ],
        "duration": 10.0,
        "checkNextImmediately": false,
        "cameraPosType": "ABSOLUTE",
        "camPosOffset": {
          "x": -512.720337,
          "y": 209.150314,
          "z": 238.108734
        },
        "camForwardTargetOffset": {
          "x": -513.309937,
          "y": 209.146683,
          "z": 237.301056
        },
        "nearLength": 0.0,
        "camTargetType": "ABSOLUTE",
        "needElev": false,
        "camFov": 30.0,
        "camDutch": 0.0,
        "lerpRatio": 0.0,
        "lerpPattern": 0,
        "cameraBlendType": "EaseInOutQuad",
        "storyDither": false,
        "cutFrameTrans": {
          "enable": false,
          "duration": 1.0
        }
      },
      {
        "$type": "ConfigDialogInterAction",
        "type": "DIALOG",
        "delayTime": 0.0,
        "aliasList": [
          "10204"
        ],
        "duration": -1.0,
        "checkNextImmediately": false,
        "dialogType": "LOCK_FRAME",
        "dialogID": 400030905,
        "protectTime": 0.0,
        "playAudio": true
      },
      {
        "$type": "ConfigEmoSyncInterAction",
        "type": "EMO_SYNC",
        "delayTime": 0.0,
        "aliasList": [
          "10204"
        ],
        "duration": -1.0,
        "checkNextImmediately": false,
        "dataPath": "Cs_Emo_Avatar_Simple_Common_Set/Cs_Emo_Avatar_Talk/Cs_Emo_Avatar_Event/Cs_Emo_Avatar_HaiDeng/Cs_Emo_400030905",
        "audioBankName": "",
        "audioName": "",
        "backType": "NONE",
        "enableBlink": true
      }
    ],
    [
      {
        "$type": "ConfigLookAtInterAction",
        "type": "LOOK_AT",
        "delayTime": 0.402840883,
        "aliasList": [
          "Avatar"
        ],
        "duration": -1.0,
        "checkNextImmediately": false,
        "enableHead": true,
        "useTargetPos": true,
        "enableAbsolute": true,
        "targetPosition": {
          "x": -513.621033,
          "y": 209.3011,
          "z": 236.8638
        },
        "targetOffset": {
          "x": 0.0,
          "y": 0.0,
          "z": 0.0
        },
        "headRotateVec": {
          "x": 0.0,
          "y": 0.0,
          "z": 0.0
        },
        "headTurnTime": 0.35,
        "enableBody": false,
        "bodyAngle": 0.0,
        "bodyTurnTime": 0.0
      },
      {
        "$type": "ConfigBodyLangInterAction",
        "type": "BODY_LANG",
        "delayTime": 0.4,
        "aliasList": [
          "1005"
        ],
        "duration": -1.0,
        "checkNextImmediately": false,
        "bodyLangParam": 0,
        "isContinue": true,
        "loopState": 0
      },
      {
        "$type": "ConfigDialogInterAction",
        "type": "DIALOG",
        "delayTime": 0.0,
        "aliasList": [
          "10204"
        ],
        "duration": -1.0,
        "checkNextImmediately": false,
        "dialogType": "LOCK_FRAME",
        "dialogID": 400030906,
        "protectTime": 1.5,
        "playAudio": true
      },
      {
        "$type": "ConfigBodyLangInterAction",
        "type": "BODY_LANG",
        "delayTime": 0.0,
        "aliasList": [
          "10204"
        ],
        "duration": -1.0,
        "checkNextImmediately": false,
        "bodyLangParam": 0,
        "isContinue": true,
        "loopState": 0
      },
      {
        "$type": "ConfigBodyLangInterAction",
        "type": "BODY_LANG",
        "delayTime": 0.7,
        "aliasList": [
          "10204"
        ],
        "duration": -1.0,
        "checkNextImmediately": false,
        "bodyLangParam": 1130,
        "isContinue": false,
        "loopState": 0
      },
      {
        "$type": "ConfigEmoSyncInterAction",
        "type": "EMO_SYNC",
        "delayTime": 0.0,
        "aliasList": [
          "10204"
        ],
        "duration": -1.0,
        "checkNextImmediately": false,
        "dataPath": "Cs_Emo_Avatar_Simple_Common_Set/Cs_Emo_Avatar_Talk/Cs_Emo_Avatar_Event/Cs_Emo_Avatar_HaiDeng/Cs_Emo_400030906",
        "audioBankName": "",
        "audioName": "",
        "backType": "NONE",
        "enableBlink": true
      }
    ],
    [
      {
        "$type": "ConfigCameraMoveInterAction",
        "type": "CAMERA_MOVE",
        "delayTime": 0.0,
        "aliasList": [
          ""
        ],
        "duration": 1.0,
        "checkNextImmediately": false,
        "cameraPosType": "ABSOLUTE",
        "camPosOffset": {
          "x": -514.7967,
          "y": 209.552155,
          "z": 237.57576
        },
        "camForwardTargetOffset": {
          "x": -513.857544,
          "y": 209.279037,
          "z": 237.367355
        },
        "nearLength": 0.0,
        "camTargetType": "ABSOLUTE",
        "needElev": false,
        "camFov": 30.0,
        "camDutch": 0.0,
        "lerpRatio": 0.0,
        "lerpPattern": 6,
        "cameraBlendType": "EaseInOutCubic",
        "storyDither": false,
        "cutFrameTrans": {
          "enable": false,
          "duration": 1.0
        }
      },
      {
        "$type": "ConfigDialogSelectAction",
        "type": "DIALOG_SELECT",
        "delayTime": 0.4,
        "aliasList": [
          "Avatar"
        ],
        "duration": -1.0,
        "checkNextImmediately": false,
        "dialogIDList": [
          400030908,
          400030909
        ],
        "grpIDList": [
          512683908,
          512683908
        ],
        "useGrpId": true
      },
      {
        "$type": "ConfigLookAtInterAction",
        "type": "LOOK_AT",
        "delayTime": 0.2341746,
        "aliasList": [
          "Avatar"
        ],
        "duration": -1.0,
        "checkNextImmediately": false,
        "enableHead": true,
        "useTargetPos": true,
        "enableAbsolute": true,
        "targetPosition": {
          "x": -512.6313,
          "y": 209.1777,
          "z": 237.354019
        },
        "targetOffset": {
          "x": 0.0,
          "y": 0.0,
          "z": 0.0
        },
        "headRotateVec": {
          "x": 0.0,
          "y": 0.0,
          "z": 0.0
        },
        "headTurnTime": 0.35,
        "enableBody": false,
        "bodyAngle": 0.0,
        "bodyTurnTime": 0.0
      },
      {
        "$type": "ConfigDialogInterAction",
        "type": "DIALOG",
        "delayTime": 0.0,
        "aliasList": [
          "1005"
        ],
        "duration": -1.0,
        "checkNextImmediately": false,
        "dialogType": "LOCK_FRAME",
        "dialogID": 400030907,
        "protectTime": 0.0,
        "playAudio": true
      },
      {
        "$type": "ConfigBodyLangInterAction",
        "type": "BODY_LANG",
        "delayTime": 0.0,
        "aliasList": [
          "1005"
        ],
        "duration": -1.0,
        "checkNextImmediately": false,
        "bodyLangParam": 1060,
        "isContinue": false,
        "loopState": 0
      },
      {
        "$type": "ConfigEmoSyncInterAction",
        "type": "EMO_SYNC",
        "delayTime": 0.0,
        "aliasList": [
          "1005"
        ],
        "duration": -1.0,
        "checkNextImmediately": false,
        "dataPath": "Cs_Emo_Avatar_Simple_Common_Set/Cs_Emo_Avatar_Talk/Cs_Emo_Avatar_Event/Cs_Emo_Avatar_HaiDeng/Cs_Emo_400030907",
        "audioBankName": "",
        "audioName": "",
        "backType": "NONE",
        "enableBlink": true
      }
    ],
    [
      {
        "$type": "ConfigCameraMoveInterAction",
        "type": "CAMERA_MOVE",
        "delayTime": 0.0,
        "aliasList": [
          ""
        ],
        "duration": 0.8,
        "checkNextImmediately": false,
        "cameraPosType": "ABSOLUTE",
        "camPosOffset": {
          "x": -515.606,
          "y": 209.6019,
          "z": 237.406342
        },
        "camForwardTargetOffset": {
          "x": -514.6423,
          "y": 209.340347,
          "z": 237.45903
        },
        "nearLength": 0.0,
        "camTargetType": "ABSOLUTE",
        "needElev": false,
        "camFov": 30.0,
        "camDutch": 0.0,
        "lerpRatio": 0.0,
        "lerpPattern": 0,
        "cameraBlendType": "EaseInOutQuad",
        "storyDither": false,
        "cutFrameTrans": {
          "enable": false,
          "duration": 1.0
        }
      },
      {
        "$type": "ConfigDialogInterAction",
        "type": "DIALOG",
        "delayTime": 0.0,
        "aliasList": [
          "1005"
        ],
        "duration": -1.0,
        "checkNextImmediately": false,
        "dialogType": "LOCK_FRAME",
        "dialogID": 400030910,
        "protectTime": 0.6,
        "playAudio": true
      },
      {
        "$type": "ConfigBodyLangInterAction",
        "type": "BODY_LANG",
        "delayTime": 0.0,
        "aliasList": [
          "1005"
        ],
        "duration": -1.0,
        "checkNextImmediately": false,
        "bodyLangParam": 1180,
        "isContinue": false,
        "loopState": 0
      },
      {
        "$type": "ConfigLookAtInterAction",
        "type": "LOOK_AT",
        "delayTime": 0.0,
        "aliasList": [
          "1005"
        ],
        "duration": -1.0,
        "checkNextImmediately": false,
        "enableHead": true,
        "useTargetPos": true,
        "enableAbsolute": true,
        "targetPosition": {
          "x": -513.6826,
          "y": 209.184,
          "z": 238.1666
        },
        "targetOffset": {
          "x": 0.0,
          "y": 0.0,
          "z": 0.0
        },
        "headRotateVec": {
          "x": 0.0,
          "y": 0.0,
          "z": 0.0
        },
        "headTurnTime": 0.35,
        "enableBody": false,
        "bodyAngle": 0.0,
        "bodyTurnTime": 0.0
      },
      {
        "$type": "ConfigEmoSyncInterAction",
        "type": "EMO_SYNC",
        "delayTime": 0.0,
        "aliasList": [
          "1005"
        ],
        "duration": -1.0,
        "checkNextImmediately": false,
        "dataPath": "Cs_Emo_Avatar_Simple_Common_Set/Cs_Emo_Avatar_Talk/Cs_Emo_Avatar_Event/Cs_Emo_Avatar_HaiDeng/Cs_Emo_400030910",
        "audioBankName": "",
        "audioName": "",
        "backType": "NONE",
        "enableBlink": true
      },
      {
        "$type": "ConfigBodyLangInterAction",
        "type": "BODY_LANG",
        "delayTime": 0.4,
        "aliasList": [
          "10204"
        ],
        "duration": -1.0,
        "checkNextImmediately": false,
        "bodyLangParam": 0,
        "isContinue": true,
        "loopState": 0
      },
      {
        "$type": "ConfigLookAtInterAction",
        "type": "LOOK_AT",
        "delayTime": 0.449192047,
        "aliasList": [
          "10204"
        ],
        "duration": -1.0,
        "checkNextImmediately": false,
        "enableHead": true,
        "useTargetPos": true,
        "enableAbsolute": true,
        "targetPosition": {
          "x": -513.6826,
          "y": 209.184,
          "z": 238.1666
        },
        "targetOffset": {
          "x": 0.0,
          "y": 0.0,
          "z": 0.0
        },
        "headRotateVec": {
          "x": 0.0,
          "y": 0.0,
          "z": 0.0
        },
        "headTurnTime": 0.4,
        "enableBody": false,
        "bodyAngle": 0.0,
        "bodyTurnTime": 0.0
      }
    ],
    [
      {
        "$type": "ConfigDialogInterAction",
        "type": "DIALOG",
        "delayTime": 0.0,
        "aliasList": [
          "1005"
        ],
        "duration": -1.0,
        "checkNextImmediately": false,
        "dialogType": "LOCK_FRAME",
        "dialogID": 400030911,
        "protectTime": 0.0,
        "playAudio": true
      },
      {
        "$type": "ConfigEmoSyncInterAction",
        "type": "EMO_SYNC",
        "delayTime": 0.0,
        "aliasList": [
          "1005"
        ],
        "duration": -1.0,
        "checkNextImmediately": false,
        "dataPath": "Cs_Emo_Avatar_Simple_Common_Set/Cs_Emo_Avatar_Talk/Cs_Emo_Avatar_Event/Cs_Emo_Avatar_HaiDeng/Cs_Emo_400030911",
        "audioBankName": "",
        "audioName": "",
        "backType": "NONE",
        "enableBlink": true
      }
    ],
    [
      {
        "$type": "ConfigDialogInterAction",
        "type": "DIALOG",
        "delayTime": 0.0,
        "aliasList": [
          "1005"
        ],
        "duration": -1.0,
        "checkNextImmediately": false,
        "dialogType": "LOCK_FRAME",
        "dialogID": 400030912,
        "protectTime": 0.5416667,
        "playAudio": true
      },
      {
        "$type": "ConfigEmoSyncInterAction",
        "type": "EMO_SYNC",
        "delayTime": 0.0,
        "aliasList": [
          "1005"
        ],
        "duration": -1.0,
        "checkNextImmediately": false,
        "dataPath": "Cs_Emo_Avatar_Simple_Common_Set/Cs_Emo_Avatar_Talk/Cs_Emo_Avatar_Event/Cs_Emo_Avatar_HaiDeng/Cs_Emo_400030912",
        "audioBankName": "",
        "audioName": "",
        "backType": "NONE",
        "enableBlink": true
      },
      {
        "$type": "ConfigBodyLangInterAction",
        "type": "BODY_LANG",
        "delayTime": 0.441666663,
        "aliasList": [
          "10204"
        ],
        "duration": -1.0,
        "checkNextImmediately": false,
        "bodyLangParam": 1120,
        "isContinue": false,
        "loopState": 0
      },
      {
        "$type": "ConfigLookAtInterAction",
        "type": "LOOK_AT",
        "delayTime": 0.311052233,
        "aliasList": [
          "10204"
        ],
        "duration": -1.0,
        "checkNextImmediately": false,
        "enableHead": true,
        "useTargetPos": true,
        "enableAbsolute": true,
        "targetPosition": {
          "x": -512.6315,
          "y": 209.177734,
          "z": 237.343536
        },
        "targetOffset": {
          "x": 0.0,
          "y": 0.0,
          "z": 0.0
        },
        "headRotateVec": {
          "x": 0.0,
          "y": 0.0,
          "z": 0.0
        },
        "headTurnTime": 0.35,
        "enableBody": false,
        "bodyAngle": 0.0,
        "bodyTurnTime": 0.0
      }
    ],
    [
      {
        "$type": "ConfigCameraMoveInterAction",
        "type": "CAMERA_MOVE",
        "delayTime": 0.0,
        "aliasList": [
          ""
        ],
        "duration": 1.0,
        "checkNextImmediately": false,
        "cameraPosType": "ABSOLUTE",
        "camPosOffset": {
          "x": -512.5188,
          "y": 209.293854,
          "z": 240.11116
        },
        "camForwardTargetOffset": {
          "x": -512.7509,
          "y": 209.128983,
          "z": 239.152557
        },
        "nearLength": 0.0,
        "camTargetType": "ABSOLUTE",
        "needElev": false,
        "camFov": 30.0,
        "camDutch": 0.0,
        "lerpRatio": 0.0,
        "lerpPattern": 6,
        "cameraBlendType": "EaseInOutCubic",
        "storyDither": false,
        "cutFrameTrans": {
          "enable": false,
          "duration": 1.0
        }
      },
      {
        "$type": "ConfigCameraMoveInterAction",
        "type": "CAMERA_MOVE",
        "delayTime": 0.1,
        "aliasList": [
          ""
        ],
        "duration": 30.0,
        "checkNextImmediately": false,
        "cameraPosType": "ABSOLUTE",
        "camPosOffset": {
          "x": -511.640381,
          "y": 209.2432,
          "z": 239.757034
        },
        "camForwardTargetOffset": {
          "x": -512.1841,
          "y": 209.090164,
          "z": 238.931824
        },
        "nearLength": 0.0,
        "camTargetType": "ABSOLUTE",
        "needElev": false,
        "camFov": 30.0,
        "camDutch": 0.0,
        "lerpRatio": 0.0,
        "lerpPattern": 0,
        "cameraBlendType": "Linear",
        "storyDither": false,
        "cutFrameTrans": {
          "enable": false,
          "duration": 1.0
        }
      },
      {
        "$type": "ConfigLookAtInterAction",
        "type": "LOOK_AT",
        "delayTime": 0.37539345,
        "aliasList": [
          "Avatar"
        ],
        "duration": -1.0,
        "checkNextImmediately": false,
        "enableHead": true,
        "useTargetPos": true,
        "enableAbsolute": true,
        "targetPosition": {
          "x": -513.621033,
          "y": 209.3011,
          "z": 236.8638
        },
        "targetOffset": {
          "x": 0.0,
          "y": 0.0,
          "z": 0.0
        },
        "headRotateVec": {
          "x": 0.0,
          "y": 0.0,
          "z": 0.0
        },
        "headTurnTime": 0.35,
        "enableBody": false,
        "bodyAngle": 0.0,
        "bodyTurnTime": 0.0
      },
      {
        "$type": "ConfigLookAtInterAction",
        "type": "LOOK_AT",
        "delayTime": 0.352255762,
        "aliasList": [
          "1005"
        ],
        "duration": -1.0,
        "checkNextImmediately": false,
        "enableHead": true,
        "useTargetPos": true,
        "enableAbsolute": true,
        "targetPosition": {
          "x": -513.621033,
          "y": 209.3011,
          "z": 236.8638
        },
        "targetOffset": {
          "x": 0.0,
          "y": 0.0,
          "z": 0.0
        },
        "headRotateVec": {
          "x": 0.0,
          "y": 0.0,
          "z": 0.0
        },
        "headTurnTime": 0.35,
        "enableBody": false,
        "bodyAngle": 0.0,
        "bodyTurnTime": 0.0
      },
      {
        "$type": "ConfigBodyLangInterAction",
        "type": "BODY_LANG",
        "delayTime": 0.333333254,
        "aliasList": [
          "1005"
        ],
        "duration": -1.0,
        "checkNextImmediately": false,
        "bodyLangParam": 0,
        "isContinue": true,
        "loopState": 0
      },
      {
        "$type": "ConfigDialogInterAction",
        "type": "DIALOG",
        "delayTime": 0.0,
        "aliasList": [
          "10204"
        ],
        "duration": -1.0,
        "checkNextImmediately": false,
        "dialogType": "LOCK_FRAME",
        "dialogID": 400030913,
        "protectTime": 0.5,
        "playAudio": true
      },
      {
        "$type": "ConfigEmoSyncInterAction",
        "type": "EMO_SYNC",
        "delayTime": 0.0,
        "aliasList": [
          "10204"
        ],
        "duration": -1.0,
        "checkNextImmediately": false,
        "dataPath": "Cs_Emo_Avatar_Simple_Common_Set/Cs_Emo_Avatar_Talk/Cs_Emo_Avatar_Event/Cs_Emo_Avatar_HaiDeng/Cs_Emo_400030913",
        "audioBankName": "",
        "audioName": "",
        "backType": "NONE",
        "enableBlink": true
      }
    ],
    [
      {
        "$type": "ConfigDialogInterAction",
        "type": "DIALOG",
        "delayTime": 0.0,
        "aliasList": [
          "1005"
        ],
        "duration": -1.0,
        "checkNextImmediately": false,
        "dialogType": "LOCK_FRAME",
        "dialogID": 400030914,
        "protectTime": 0.0,
        "playAudio": true
      },
      {
        "$type": "ConfigBodyLangInterAction",
        "type": "BODY_LANG",
        "delayTime": 0.0,
        "aliasList": [
          "1005"
        ],
        "duration": -1.0,
        "checkNextImmediately": false,
        "bodyLangParam": 1050,
        "isContinue": false,
        "loopState": 0
      },
      {
        "$type": "ConfigEmoSyncInterAction",
        "type": "EMO_SYNC",
        "delayTime": 0.0,
        "aliasList": [
          "1005"
        ],
        "duration": -1.0,
        "checkNextImmediately": false,
        "dataPath": "Cs_Emo_Avatar_Simple_Common_Set/Cs_Emo_Avatar_Talk/Cs_Emo_Avatar_Event/Cs_Emo_Avatar_HaiDeng/Cs_Emo_400030914",
        "audioBankName": "",
        "audioName": "",
        "backType": "NONE",
        "enableBlink": true
      }
    ],
    [
      {
        "$type": "ConfigDialogInterAction",
        "type": "DIALOG",
        "delayTime": 0.0,
        "aliasList": [
          "1005"
        ],
        "duration": -1.0,
        "checkNextImmediately": false,
        "dialogType": "LOCK_FRAME",
        "dialogID": 400030915,
        "protectTime": 0.0,
        "playAudio": true
      },
      {
        "$type": "ConfigBodyLangInterAction",
        "type": "BODY_LANG",
        "delayTime": 0.0,
        "aliasList": [
          "1005"
        ],
        "duration": -1.0,
        "checkNextImmediately": false,
        "bodyLangParam": 1230,
        "isContinue": false,
        "loopState": 0
      },
      {
        "$type": "ConfigEmoSyncInterAction",
        "type": "EMO_SYNC",
        "delayTime": 0.0,
        "aliasList": [
          "1005"
        ],
        "duration": -1.0,
        "checkNextImmediately": false,
        "dataPath": "Cs_Emo_Avatar_Simple_Common_Set/Cs_Emo_Avatar_Talk/Cs_Emo_Avatar_Event/Cs_Emo_Avatar_HaiDeng/Cs_Emo_400030915",
        "audioBankName": "",
        "audioName": "",
        "backType": "NONE",
        "enableBlink": true
      }
    ],
    [
      {
        "$type": "ConfigDialogInterAction",
        "type": "DIALOG",
        "delayTime": 0.0,
        "aliasList": [
          "10204"
        ],
        "duration": -1.0,
        "checkNextImmediately": false,
        "dialogType": "LOCK_FRAME",
        "dialogID": 400030916,
        "protectTime": 0.0,
        "playAudio": true
      },
      {
        "$type": "ConfigLookAtInterAction",
        "type": "LOOK_AT",
        "delayTime": 0.0,
        "aliasList": [
          "10204"
        ],
        "duration": -1.0,
        "checkNextImmediately": false,
        "enableHead": true,
        "useTargetPos": false,
        "enableAbsolute": true,
        "targetPosition": {
          "x": -513.4061,
          "y": 209.051208,
          "z": 236.733582
        },
        "targetOffset": {
          "x": 0.0,
          "y": 0.0,
          "z": 0.0
        },
        "headRotateVec": {
          "x": 37.4154663,
          "y": 24.2103844,
          "z": 0.0
        },
        "headTurnTime": 0.4,
        "enableBody": false,
        "bodyAngle": 0.0,
        "bodyTurnTime": 0.0
      },
      {
        "$type": "ConfigEmoSyncInterAction",
        "type": "EMO_SYNC",
        "delayTime": 0.0,
        "aliasList": [
          "10204"
        ],
        "duration": -1.0,
        "checkNextImmediately": false,
        "dataPath": "Cs_Emo_Avatar_Simple_Common_Set/Cs_Emo_Avatar_Talk/Cs_Emo_Avatar_Event/Cs_Emo_Avatar_HaiDeng/Cs_Emo_400030916",
        "audioBankName": "",
        "audioName": "",
        "backType": "NONE",
        "enableBlink": true
      }
    ],
    [
      {
        "$type": "ConfigDialogInterAction",
        "type": "DIALOG",
        "delayTime": 0.0,
        "aliasList": [
          "1005"
        ],
        "duration": -1.0,
        "checkNextImmediately": false,
        "dialogType": "LOCK_FRAME",
        "dialogID": 400030917,
        "protectTime": 0.0,
        "playAudio": true
      },
      {
        "$type": "ConfigBodyLangInterAction",
        "type": "BODY_LANG",
        "delayTime": 0.0,
        "aliasList": [
          "1005"
        ],
        "duration": -1.0,
        "checkNextImmediately": false,
        "bodyLangParam": 1180,
        "isContinue": false,
        "loopState": 0
      },
      {
        "$type": "ConfigEmoSyncInterAction",
        "type": "EMO_SYNC",
        "delayTime": 0.0,
        "aliasList": [
          "1005"
        ],
        "duration": -1.0,
        "checkNextImmediately": false,
        "dataPath": "Cs_Emo_Avatar_Simple_Common_Set/Cs_Emo_Avatar_Talk/Cs_Emo_Avatar_Event/Cs_Emo_Avatar_HaiDeng/Cs_Emo_400030917",
        "audioBankName": "",
        "audioName": "",
        "backType": "NONE",
        "enableBlink": true
      }
    ],
    [
      {
        "$type": "ConfigCameraMoveInterAction",
        "type": "CAMERA_MOVE",
        "delayTime": 0.0,
        "aliasList": [
          ""
        ],
        "duration": 1.5,
        "checkNextImmediately": false,
        "cameraPosType": "ABSOLUTE",
        "camPosOffset": {
          "x": -512.794861,
          "y": 209.115677,
          "z": 238.475723
        },
        "camForwardTargetOffset": {
          "x": -513.288757,
          "y": 209.121048,
          "z": 237.606216
        },
        "nearLength": 0.0,
        "camTargetType": "ABSOLUTE",
        "needElev": false,
        "camFov": 30.0,
        "camDutch": 0.0,
        "lerpRatio": 0.0,
        "lerpPattern": 0,
        "cameraBlendType": "EaseOutQuart",
        "storyDither": false,
        "cutFrameTrans": {
          "enable": false,
          "duration": 1.0
        }
      },
      {
        "$type": "ConfigBodyLangInterAction",
        "type": "BODY_LANG",
        "delayTime": 0.4,
        "aliasList": [
          "1005"
        ],
        "duration": -1.0,
        "checkNextImmediately": false,
        "bodyLangParam": 0,
        "isContinue": true,
        "loopState": 0
      },
      {
        "$type": "ConfigDialogInterAction",
        "type": "DIALOG",
        "delayTime": 0.0,
        "aliasList": [
          "10204"
        ],
        "duration": -1.0,
        "checkNextImmediately": false,
        "dialogType": "LOCK_FRAME",
        "dialogID": 400030918,
        "protectTime": 0.5,
        "playAudio": true
      },
      {
        "$type": "ConfigLookAtInterAction",
        "type": "LOOK_AT",
        "delayTime": 0.0,
        "aliasList": [
          "10204"
        ],
        "duration": -1.0,
        "checkNextImmediately": false,
        "enableHead": true,
        "useTargetPos": true,
        "enableAbsolute": true,
        "targetPosition": {
          "x": -512.6315,
          "y": 209.177734,
          "z": 237.343536
        },
        "targetOffset": {
          "x": 0.0,
          "y": 0.0,
          "z": 0.0
        },
        "headRotateVec": {
          "x": 0.0,
          "y": 0.0,
          "z": 0.0
        },
        "headTurnTime": 0.35,
        "enableBody": false,
        "bodyAngle": 0.0,
        "bodyTurnTime": 0.0
      },
      {
        "$type": "ConfigEmoSyncInterAction",
        "type": "EMO_SYNC",
        "delayTime": 0.0,
        "aliasList": [
          "10204"
        ],
        "duration": -1.0,
        "checkNextImmediately": false,
        "dataPath": "Cs_Emo_Avatar_Simple_Common_Set/Cs_Emo_Avatar_Talk/Cs_Emo_Avatar_Event/Cs_Emo_Avatar_HaiDeng/Cs_Emo_400030918",
        "audioBankName": "",
        "audioName": "",
        "backType": "NONE",
        "enableBlink": true
      }
    ],
    [
      {
        "$type": "ConfigDialogInterAction",
        "type": "DIALOG",
        "delayTime": 0.0,
        "aliasList": [
          "10204"
        ],
        "duration": -1.0,
        "checkNextImmediately": false,
        "dialogType": "LOCK_FRAME",
        "dialogID": 400030919,
        "protectTime": 0.0,
        "playAudio": true
      },
      {
        "$type": "ConfigEmoSyncInterAction",
        "type": "EMO_SYNC",
        "delayTime": 0.0,
        "aliasList": [
          "10204"
        ],
        "duration": -1.0,
        "checkNextImmediately": false,
        "dataPath": "Cs_Emo_Avatar_Simple_Common_Set/Cs_Emo_Avatar_Talk/Cs_Emo_Avatar_Event/Cs_Emo_Avatar_HaiDeng/Cs_Emo_400030919",
        "audioBankName": "",
        "audioName": "",
        "backType": "NONE",
        "enableBlink": true
      }
    ],
    [
      {
        "$type": "ConfigCameraMoveInterAction",
        "type": "CAMERA_MOVE",
        "delayTime": 0.0,
        "aliasList": [
          ""
        ],
        "duration": 1.0,
        "checkNextImmediately": false,
        "cameraPosType": "ABSOLUTE",
        "camPosOffset": {
          "x": -512.284058,
          "y": 209.688354,
          "z": 235.525833
        },
        "camForwardTargetOffset": {
          "x": -512.7229,
          "y": 209.383652,
          "z": 236.37117
        },
        "nearLength": 0.0,
        "camTargetType": "ABSOLUTE",
        "needElev": false,
        "camFov": 30.0,
        "camDutch": 0.0,
        "lerpRatio": 0.0,
        "lerpPattern": 6,
        "cameraBlendType": "EaseInOutCubic",
        "storyDither": false,
        "cutFrameTrans": {
          "enable": false,
          "duration": 1.0
        }
      },
      {
        "$type": "ConfigCameraMoveInterAction",
        "type": "CAMERA_MOVE",
        "delayTime": 0.1,
        "aliasList": [
          ""
        ],
        "duration": 15.0,
        "checkNextImmediately": false,
        "cameraPosType": "ABSOLUTE",
        "camPosOffset": {
          "x": -512.0518,
          "y": 209.6992,
          "z": 235.66275
        },
        "camForwardTargetOffset": {
          "x": -512.591064,
          "y": 209.3945,
          "z": 236.447861
        },
        "nearLength": 0.0,
        "camTargetType": "ABSOLUTE",
        "needElev": false,
        "camFov": 30.0,
        "camDutch": 0.0,
        "lerpRatio": 0.0,
        "lerpPattern": 0,
        "cameraBlendType": "EaseInOutQuad",
        "storyDither": false,
        "cutFrameTrans": {
          "enable": false,
          "duration": 1.0
        }
      },
      {
        "$type": "ConfigDialogInterAction",
        "type": "DIALOG",
        "delayTime": 0.0,
        "aliasList": [
          "10204"
        ],
        "duration": -1.0,
        "checkNextImmediately": false,
        "dialogType": "LOCK_FRAME",
        "dialogID": 400030920,
        "protectTime": 0.0,
        "playAudio": true
      },
      {
        "$type": "ConfigLookAtInterAction",
        "type": "LOOK_AT",
        "delayTime": 0.0,
        "aliasList": [
          "10204"
        ],
        "duration": -1.0,
        "checkNextImmediately": false,
        "enableHead": true,
        "useTargetPos": true,
        "enableAbsolute": true,
        "targetPosition": {
          "x": -513.6826,
          "y": 209.184,
          "z": 238.1666
        },
        "targetOffset": {
          "x": 0.0,
          "y": 0.0,
          "z": 0.0
        },
        "headRotateVec": {
          "x": 0.0,
          "y": 0.0,
          "z": 0.0
        },
        "headTurnTime": 0.35,
        "enableBody": false,
        "bodyAngle": 0.0,
        "bodyTurnTime": 0.0
      },
      {
        "$type": "ConfigEmoSyncInterAction",
        "type": "EMO_SYNC",
        "delayTime": 0.0,
        "aliasList": [
          "10204"
        ],
        "duration": -1.0,
        "checkNextImmediately": false,
        "dataPath": "Cs_Emo_Avatar_Simple_Common_Set/Cs_Emo_Avatar_Talk/Cs_Emo_Avatar_Event/Cs_Emo_Avatar_HaiDeng/Cs_Emo_400030920",
        "audioBankName": "",
        "audioName": "",
        "backType": "NONE",
        "enableBlink": true
      }
    ],
    [
      {
        "$type": "ConfigLookAtInterAction",
        "type": "LOOK_AT",
        "delayTime": 0.4300227,
        "aliasList": [
          "1005"
        ],
        "duration": -1.0,
        "checkNextImmediately": false,
        "enableHead": true,
        "useTargetPos": true,
        "enableAbsolute": true,
        "targetPosition": {
          "x": -513.6826,
          "y": 209.184,
          "z": 238.1666
        },
        "targetOffset": {
          "x": 0.0,
          "y": 0.0,
          "z": 0.0
        },
        "headRotateVec": {
          "x": 0.0,
          "y": 0.0,
          "z": 0.0
        },
        "headTurnTime": 0.35,
        "enableBody": false,
        "bodyAngle": 0.0,
        "bodyTurnTime": 0.0
      },
      {
        "$type": "ConfigBodyLangInterAction",
        "type": "BODY_LANG",
        "delayTime": 0.45,
        "aliasList": [
          "1005"
        ],
        "duration": -1.0,
        "checkNextImmediately": false,
        "bodyLangParam": 1130,
        "isContinue": false,
        "loopState": 0
      },
      {
        "$type": "ConfigDialogInterAction",
        "type": "DIALOG",
        "delayTime": 0.0,
        "aliasList": [
          "10204"
        ],
        "duration": -1.0,
        "checkNextImmediately": false,
        "dialogType": "LOCK_FRAME",
        "dialogID": 400030921,
        "protectTime": 1.0,
        "playAudio": true
      },
      {
        "$type": "ConfigEmoSyncInterAction",
        "type": "EMO_SYNC",
        "delayTime": 0.0,
        "aliasList": [
          "10204"
        ],
        "duration": -1.0,
        "checkNextImmediately": false,
        "dataPath": "Cs_Emo_Avatar_Simple_Common_Set/Cs_Emo_Avatar_Talk/Cs_Emo_Avatar_Event/Cs_Emo_Avatar_HaiDeng/Cs_Emo_400030921",
        "audioBankName": "",
        "audioName": "",
        "backType": "NONE",
        "enableBlink": true
      },
      {
        "$type": "ConfigBodyLangInterAction",
        "type": "BODY_LANG",
        "delayTime": 0.0,
        "aliasList": [
          "10204"
        ],
        "duration": -1.0,
        "checkNextImmediately": false,
        "bodyLangParam": 1121,
        "isContinue": false,
        "loopState": 0
      }
    ],
    [
      {
        "$type": "ConfigDialogInterAction",
        "type": "DIALOG",
        "delayTime": 0.0,
        "aliasList": [
          "10204"
        ],
        "duration": -1.0,
        "checkNextImmediately": false,
        "dialogType": "LOCK_FRAME",
        "dialogID": 400030922,
        "protectTime": 0.0,
        "playAudio": true
      },
      {
        "$type": "ConfigEmoSyncInterAction",
        "type": "EMO_SYNC",
        "delayTime": 0.0,
        "aliasList": [
          "10204"
        ],
        "duration": -1.0,
        "checkNextImmediately": false,
        "dataPath": "Cs_Emo_Avatar_Simple_Common_Set/Cs_Emo_Avatar_Talk/Cs_Emo_Avatar_Event/Cs_Emo_Avatar_HaiDeng/Cs_Emo_400030922",
        "audioBankName": "",
        "audioName": "",
        "backType": "NONE",
        "enableBlink": true
      },
      {
        "$type": "ConfigBodyLangInterAction",
        "type": "BODY_LANG",
        "delayTime": 0.0,
        "aliasList": [
          "10204"
        ],
        "duration": -1.0,
        "checkNextImmediately": false,
        "bodyLangParam": 0,
        "isContinue": true,
        "loopState": 0
      }
    ],
    [
      {
        "$type": "ConfigCameraMoveInterAction",
        "type": "CAMERA_MOVE",
        "delayTime": 0.0,
        "aliasList": [
          ""
        ],
        "duration": 1.0,
        "checkNextImmediately": false,
        "cameraPosType": "ABSOLUTE",
        "camPosOffset": {
          "x": -513.105347,
          "y": 211.338455,
          "z": 240.3785
        },
        "camForwardTargetOffset": {
          "x": -513.1899,
          "y": 210.678589,
          "z": 239.631882
        },
        "nearLength": 0.0,
        "camTargetType": "ABSOLUTE",
        "needElev": false,
        "camFov": 30.0,
        "camDutch": 0.0,
        "lerpRatio": 0.0,
        "lerpPattern": 6,
        "cameraBlendType": "EaseInOutCubic",
        "storyDither": false,
        "cutFrameTrans": {
          "enable": false,
          "duration": 1.0
        }
      },
      {
        "$type": "ConfigCameraMoveInterAction",
        "type": "CAMERA_MOVE",
        "delayTime": 0.1,
        "aliasList": [
          ""
        ],
        "duration": 3.0,
        "checkNextImmediately": false,
        "cameraPosType": "ABSOLUTE",
        "camPosOffset": {
          "x": -513.132568,
          "y": 211.2712,
          "z": 240.266342
        },
        "camForwardTargetOffset": {
          "x": -513.2171,
          "y": 210.611328,
          "z": 239.51973
        },
        "nearLength": 0.0,
        "camTargetType": "ABSOLUTE",
        "needElev": false,
        "camFov": 30.0,
        "camDutch": 0.0,
        "lerpRatio": 0.0,
        "lerpPattern": 0,
        "cameraBlendType": "EaseInOutQuad",
        "storyDither": false,
        "cutFrameTrans": {
          "enable": false,
          "duration": 1.0
        }
      },
      {
        "$type": "ConfigLookAtInterAction",
        "type": "LOOK_AT",
        "delayTime": 0.3039734,
        "aliasList": [
          "Avatar"
        ],
        "duration": -1.0,
        "checkNextImmediately": false,
        "enableHead": true,
        "useTargetPos": true,
        "enableAbsolute": true,
        "targetPosition": {
          "x": -512.9,
          "y": 207.8,
          "z": 236.5
        },
        "targetOffset": {
          "x": 0.0,
          "y": 0.0,
          "z": 0.0
        },
        "headRotateVec": {
          "x": 0.0,
          "y": 0.0,
          "z": 0.0
        },
        "headTurnTime": 0.4,
        "enableBody": false,
        "bodyAngle": 0.0,
        "bodyTurnTime": 0.0
      },
      {
        "$type": "ConfigDialogInterAction",
        "type": "DIALOG",
        "delayTime": 0.0,
        "aliasList": [
          "1005"
        ],
        "duration": -1.0,
        "checkNextImmediately": false,
        "dialogType": "LOCK_FRAME",
        "dialogID": 400030923,
        "protectTime": 0.5,
        "playAudio": true
      },
      {
        "$type": "ConfigBodyLangInterAction",
        "type": "BODY_LANG",
        "delayTime": 0.0,
        "aliasList": [
          "1005"
        ],
        "duration": -1.0,
        "checkNextImmediately": false,
        "bodyLangParam": 1060,
        "isContinue": false,
        "loopState": 0
      },
      {
        "$type": "ConfigLookAtInterAction",
        "type": "LOOK_AT",
        "delayTime": 0.0,
        "aliasList": [
          "1005"
        ],
        "duration": -1.0,
        "checkNextImmediately": false,
        "enableHead": true,
        "useTargetPos": true,
        "enableAbsolute": true,
        "targetPosition": {
          "x": -512.9,
          "y": 207.8,
          "z": 236.5
        },
        "targetOffset": {
          "x": 0.0,
          "y": 0.0,
          "z": 0.0
        },
        "headRotateVec": {
          "x": 0.0,
          "y": 0.0,
          "z": 0.0
        },
        "headTurnTime": 0.4,
        "enableBody": false,
        "bodyAngle": 0.0,
        "bodyTurnTime": 0.0
      },
      {
        "$type": "ConfigEmoSyncInterAction",
        "type": "EMO_SYNC",
        "delayTime": 0.0,
        "aliasList": [
          "1005"
        ],
        "duration": -1.0,
        "checkNextImmediately": false,
        "dataPath": "Cs_Emo_Avatar_Simple_Common_Set/Cs_Emo_Avatar_Talk/Cs_Emo_Avatar_Event/Cs_Emo_Avatar_HaiDeng/Cs_Emo_400030923",
        "audioBankName": "",
        "audioName": "",
        "backType": "NONE",
        "enableBlink": true
      },
      {
        "$type": "ConfigBodyLangInterAction",
        "type": "BODY_LANG",
        "delayTime": 0.4,
        "aliasList": [
          "10204"
        ],
        "duration": -1.0,
        "checkNextImmediately": false,
        "bodyLangParam": 0,
        "isContinue": true,
        "loopState": 0
      },
      {
        "$type": "ConfigLookAtInterAction",
        "type": "LOOK_AT",
        "delayTime": 0.353968322,
        "aliasList": [
          "10204"
        ],
        "duration": -1.0,
        "checkNextImmediately": false,
        "enableHead": true,
        "useTargetPos": true,
        "enableAbsolute": true,
        "targetPosition": {
          "x": -512.9,
          "y": 207.8,
          "z": 236.5
        },
        "targetOffset": {
          "x": 0.0,
          "y": 0.0,
          "z": 0.0
        },
        "headRotateVec": {
          "x": 0.0,
          "y": 0.0,
          "z": 0.0
        },
        "headTurnTime": 0.4,
        "enableBody": false,
        "bodyAngle": 0.0,
        "bodyTurnTime": 0.0
      }
    ],
    [
      {
        "$type": "ConfigDialogSelectAction",
        "type": "DIALOG_SELECT",
        "delayTime": 0.4,
        "aliasList": [
          "Avatar"
        ],
        "duration": -1.0,
        "checkNextImmediately": false,
        "dialogIDList": [
          400030925
        ],
        "grpIDList": [
          3008299095
        ],
        "useGrpId": true
      },
      {
        "$type": "ConfigDialogInterAction",
        "type": "DIALOG",
        "delayTime": 0.0,
        "aliasList": [
          "10204"
        ],
        "duration": -1.0,
        "checkNextImmediately": false,
        "dialogType": "LOCK_FRAME",
        "dialogID": 400030924,
        "protectTime": 0.0,
        "playAudio": true
      },
      {
        "$type": "ConfigEmoSyncInterAction",
        "type": "EMO_SYNC",
        "delayTime": 0.0,
        "aliasList": [
          "10204"
        ],
        "duration": -1.0,
        "checkNextImmediately": false,
        "dataPath": "Cs_Emo_Avatar_Simple_Common_Set/Cs_Emo_Avatar_Talk/Cs_Emo_Avatar_Event/Cs_Emo_Avatar_HaiDeng/Cs_Emo_400030924",
        "audioBankName": "",
        "audioName": "",
        "backType": "NONE",
        "enableBlink": true
      }
    ],
    [
      {
        "$type": "ConfigDialogInterAction",
        "type": "DIALOG",
        "delayTime": 0.0,
        "aliasList": [
          "1005"
        ],
        "duration": -1.0,
        "checkNextImmediately": false,
        "dialogType": "LOCK_FRAME",
        "dialogID": 400030926,
        "protectTime": 0.0,
        "playAudio": true
      },
      {
        "$type": "ConfigBodyLangInterAction",
        "type": "BODY_LANG",
        "delayTime": 0.0,
        "aliasList": [
          "1005"
        ],
        "duration": -1.0,
        "checkNextImmediately": false,
        "bodyLangParam": 1110,
        "isContinue": false,
        "loopState": 0
      },
      {
        "$type": "ConfigEmoSyncInterAction",
        "type": "EMO_SYNC",
        "delayTime": 0.0,
        "aliasList": [
          "1005"
        ],
        "duration": -1.0,
        "checkNextImmediately": false,
        "dataPath": "Cs_Emo_Avatar_Simple_Common_Set/Cs_Emo_Avatar_Talk/Cs_Emo_Avatar_Event/Cs_Emo_Avatar_HaiDeng/Cs_Emo_400030926",
        "audioBankName": "",
        "audioName": "",
        "backType": "NONE",
        "enableBlink": true
      }
    ],
    [
      {
        "$type": "ConfigCameraMoveInterAction",
        "type": "CAMERA_MOVE",
        "delayTime": 0.0,
        "aliasList": [
          ""
        ],
        "duration": 1.0,
        "checkNextImmediately": false,
        "cameraPosType": "ABSOLUTE",
        "camPosOffset": {
          "x": -515.4861,
          "y": 209.437668,
          "z": 238.947739
        },
        "camForwardTargetOffset": {
          "x": -514.6962,
          "y": 209.228592,
          "z": 238.37117
        },
        "nearLength": 0.0,
        "camTargetType": "ABSOLUTE",
        "needElev": false,
        "camFov": 30.0,
        "camDutch": 0.0,
        "lerpRatio": 0.0,
        "lerpPattern": 6,
        "cameraBlendType": "EaseInOutCubic",
        "storyDither": false,
        "cutFrameTrans": {
          "enable": false,
          "duration": 1.0
        }
      },
      {
        "$type": "ConfigCameraMoveInterAction",
        "type": "CAMERA_MOVE",
        "delayTime": 0.1,
        "aliasList": [
          ""
        ],
        "duration": 15.0,
        "checkNextImmediately": false,
        "cameraPosType": "ABSOLUTE",
        "camPosOffset": {
          "x": -515.649048,
          "y": 209.44664,
          "z": 238.695053
        },
        "camForwardTargetOffset": {
          "x": -514.787964,
          "y": 209.234634,
          "z": 238.232925
        },
        "nearLength": 0.0,
        "camTargetType": "ABSOLUTE",
        "needElev": false,
        "camFov": 30.0,
        "camDutch": 0.0,
        "lerpRatio": 0.0,
        "lerpPattern": 0,
        "cameraBlendType": "EaseInOutQuad",
        "storyDither": false,
        "cutFrameTrans": {
          "enable": false,
          "duration": 1.0
        }
      },
      {
        "$type": "ConfigLookAtInterAction",
        "type": "LOOK_AT",
        "delayTime": 0.319223046,
        "aliasList": [
          "Avatar"
        ],
        "duration": -1.0,
        "checkNextImmediately": false,
        "enableHead": true,
        "useTargetPos": true,
        "enableAbsolute": true,
        "targetPosition": {
          "x": -513.621033,
          "y": 209.3011,
          "z": 236.8638
        },
        "targetOffset": {
          "x": 0.0,
          "y": 0.0,
          "z": 0.0
        },
        "headRotateVec": {
          "x": 0.0,
          "y": 0.0,
          "z": 0.0
        },
        "headTurnTime": 0.35,
        "enableBody": false,
        "bodyAngle": 0.0,
        "bodyTurnTime": 0.0
      },
      {
        "$type": "ConfigLookAtInterAction",
        "type": "LOOK_AT",
        "delayTime": 0.427550256,
        "aliasList": [
          "1005"
        ],
        "duration": -1.0,
        "checkNextImmediately": false,
        "enableHead": true,
        "useTargetPos": true,
        "enableAbsolute": true,
        "targetPosition": {
          "x": -513.621033,
          "y": 209.3011,
          "z": 236.8638
        },
        "targetOffset": {
          "x": 0.0,
          "y": 0.0,
          "z": 0.0
        },
        "headRotateVec": {
          "x": 0.0,
          "y": 0.0,
          "z": 0.0
        },
        "headTurnTime": 0.35,
        "enableBody": false,
        "bodyAngle": 0.0,
        "bodyTurnTime": 0.0
      },
      {
        "$type": "ConfigBodyLangInterAction",
        "type": "BODY_LANG",
        "delayTime": 0.469229132,
        "aliasList": [
          "1005"
        ],
        "duration": -1.0,
        "checkNextImmediately": false,
        "bodyLangParam": 0,
        "isContinue": true,
        "loopState": 0
      },
      {
        "$type": "ConfigDialogInterAction",
        "type": "DIALOG",
        "delayTime": 0.0,
        "aliasList": [
          "10204"
        ],
        "duration": -1.0,
        "checkNextImmediately": false,
        "dialogType": "LOCK_FRAME",
        "dialogID": 400030927,
        "protectTime": 0.7,
        "playAudio": true
      },
      {
        "$type": "ConfigLookAtInterAction",
        "type": "LOOK_AT",
        "delayTime": 0.0,
        "aliasList": [
          "10204"
        ],
        "duration": -1.0,
        "checkNextImmediately": false,
        "enableHead": true,
        "useTargetPos": true,
        "enableAbsolute": true,
        "targetPosition": {
          "x": -513.6826,
          "y": 209.184,
          "z": 238.1666
        },
        "targetOffset": {
          "x": 0.0,
          "y": 0.0,
          "z": 0.0
        },
        "headRotateVec": {
          "x": 0.0,
          "y": 0.0,
          "z": 0.0
        },
        "headTurnTime": 0.35,
        "enableBody": false,
        "bodyAngle": 0.0,
        "bodyTurnTime": 0.0
      },
      {
        "$type": "ConfigBodyLangInterAction",
        "type": "BODY_LANG",
        "delayTime": 0.0,
        "aliasList": [
          "10204"
        ],
        "duration": -1.0,
        "checkNextImmediately": false,
        "bodyLangParam": 1170,
        "isContinue": false,
        "loopState": 0
      },
      {
        "$type": "ConfigEmoSyncInterAction",
        "type": "EMO_SYNC",
        "delayTime": 0.0,
        "aliasList": [
          "10204"
        ],
        "duration": -1.0,
        "checkNextImmediately": false,
        "dataPath": "Cs_Emo_Avatar_Simple_Common_Set/Cs_Emo_Avatar_Talk/Cs_Emo_Avatar_Event/Cs_Emo_Avatar_HaiDeng/Cs_Emo_400030927",
        "audioBankName": "",
        "audioName": "",
        "backType": "NONE",
        "enableBlink": true
      }
    ],
    [
      {
        "$type": "ConfigDialogSelectAction",
        "type": "DIALOG_SELECT",
        "delayTime": 0.4,
        "aliasList": [
          "Avatar"
        ],
        "duration": -1.0,
        "checkNextImmediately": false,
        "dialogIDList": [
          400030929
        ],
        "grpIDList": [
          3008299098
        ],
        "useGrpId": true
      },
      {
        "$type": "ConfigDialogInterAction",
        "type": "DIALOG",
        "delayTime": 0.0,
        "aliasList": [
          "10204"
        ],
        "duration": -1.0,
        "checkNextImmediately": false,
        "dialogType": "LOCK_FRAME",
        "dialogID": 400030928,
        "protectTime": 0.0,
        "playAudio": true
      },
      {
        "$type": "ConfigEmoSyncInterAction",
        "type": "EMO_SYNC",
        "delayTime": 0.0,
        "aliasList": [
          "10204"
        ],
        "duration": -1.0,
        "checkNextImmediately": false,
        "dataPath": "Cs_Emo_Avatar_Simple_Common_Set/Cs_Emo_Avatar_Talk/Cs_Emo_Avatar_Event/Cs_Emo_Avatar_HaiDeng/Cs_Emo_400030928",
        "audioBankName": "",
        "audioName": "",
        "backType": "NONE",
        "enableBlink": true
      }
    ],
    [
      {
        "$type": "ConfigDialogInterAction",
        "type": "DIALOG",
        "delayTime": 0.0,
        "aliasList": [
          "1005"
        ],
        "duration": -1.0,
        "checkNextImmediately": false,
        "dialogType": "LOCK_FRAME",
        "dialogID": 400030930,
        "protectTime": 0.0,
        "playAudio": true
      },
      {
        "$type": "ConfigBodyLangInterAction",
        "type": "BODY_LANG",
        "delayTime": 0.0,
        "aliasList": [
          "1005"
        ],
        "duration": -1.0,
        "checkNextImmediately": false,
        "bodyLangParam": 1040,
        "isContinue": false,
        "loopState": 0
      },
      {
        "$type": "ConfigEmoSyncInterAction",
        "type": "EMO_SYNC",
        "delayTime": 0.0,
        "aliasList": [
          "1005"
        ],
        "duration": -1.0,
        "checkNextImmediately": false,
        "dataPath": "Cs_Emo_Avatar_Simple_Common_Set/Cs_Emo_Avatar_Talk/Cs_Emo_Avatar_Event/Cs_Emo_Avatar_HaiDeng/Cs_Emo_400030930",
        "audioBankName": "",
        "audioName": "",
        "backType": "NONE",
        "enableBlink": true
      },
      {
        "$type": "ConfigBodyLangInterAction",
        "type": "BODY_LANG",
        "delayTime": 0.4,
        "aliasList": [
          "10204"
        ],
        "duration": -1.0,
        "checkNextImmediately": false,
        "bodyLangParam": 0,
        "isContinue": true,
        "loopState": 0
      }
    ],
    [
      {
        "$type": "ConfigDialogInterAction",
        "type": "DIALOG",
        "delayTime": 0.0,
        "aliasList": [
          "1005"
        ],
        "duration": -1.0,
        "checkNextImmediately": false,
        "dialogType": "LOCK_FRAME",
        "dialogID": 400030931,
        "protectTime": 0.6,
        "playAudio": true
      },
      {
        "$type": "ConfigBodyLangInterAction",
        "type": "BODY_LANG",
        "delayTime": 0.0,
        "aliasList": [
          "1005"
        ],
        "duration": -1.0,
        "checkNextImmediately": false,
        "bodyLangParam": 1170,
        "isContinue": false,
        "loopState": 0
      },
      {
        "$type": "ConfigBodyLangInterAction",
        "type": "BODY_LANG",
        "delayTime": 2.72499943,
        "aliasList": [
          "1005"
        ],
        "duration": -1.0,
        "checkNextImmediately": false,
        "bodyLangParam": 1150,
        "isContinue": false,
        "loopState": 0
      },
      {
        "$type": "ConfigBodyLangInterAction",
        "type": "BODY_LANG",
        "delayTime": 4.78333426,
        "aliasList": [
          "1005"
        ],
        "duration": -1.0,
        "checkNextImmediately": false,
        "bodyLangParam": 1060,
        "isContinue": false,
        "loopState": 0
      },
      {
        "$type": "ConfigEmoSyncInterAction",
        "type": "EMO_SYNC",
        "delayTime": 0.0,
        "aliasList": [
          "1005"
        ],
        "duration": -1.0,
        "checkNextImmediately": false,
        "dataPath": "Cs_Emo_Avatar_Simple_Common_Set/Cs_Emo_Avatar_Talk/Cs_Emo_Avatar_Event/Cs_Emo_Avatar_HaiDeng/Cs_Emo_400030931",
        "audioBankName": "",
        "audioName": "",
        "backType": "NONE",
        "enableBlink": true
      },
      {
        "$type": "ConfigLookAtInterAction",
        "type": "LOOK_AT",
        "delayTime": 0.405300915,
        "aliasList": [
          "10204"
        ],
        "duration": -1.0,
        "checkNextImmediately": false,
        "enableHead": true,
        "useTargetPos": true,
        "enableAbsolute": true,
        "targetPosition": {
          "x": -512.6315,
          "y": 209.177734,
          "z": 237.343536
        },
        "targetOffset": {
          "x": 0.0,
          "y": 0.0,
          "z": 0.0
        },
        "headRotateVec": {
          "x": 0.0,
          "y": 0.0,
          "z": 0.0
        },
        "headTurnTime": 0.35,
        "enableBody": false,
        "bodyAngle": 0.0,
        "bodyTurnTime": 0.0
      }
    ],
    [
      {
        "$type": "ConfigDialogInterAction",
        "type": "DIALOG_CLEAR",
        "delayTime": 0.3,
        "aliasList": [
          ""
        ],
        "duration": -1.0,
        "checkNextImmediately": false,
        "dialogType": "LOCK_FRAME",
        "dialogID": 400030931,
        "protectTime": 0.0,
        "playAudio": true
      },
      {
        "$type": "ConfigCameraMoveInterAction",
        "type": "CAMERA_MOVE",
        "delayTime": 0.5,
        "aliasList": [
          ""
        ],
        "duration": 0.5,
        "checkNextImmediately": false,
        "cameraPosType": "EXIT",
        "camPosOffset": {
          "x": 0.0,
          "y": 0.0,
          "z": 0.0
        },
        "camForwardTargetOffset": {
          "x": 0.0,
          "y": 0.0,
          "z": 0.0
        },
        "nearLength": 0.0,
        "camTargetType": "TO_INTEE",
        "needElev": false,
        "camFov": 45.0,
        "camDutch": 0.0,
        "lerpRatio": 0.0,
        "lerpPattern": 6,
        "cameraBlendType": "EaseInOutCubic",
        "storyDither": false,
        "cutFrameTrans": {
          "enable": false,
          "duration": 1.0
        }
      },
      {
        "$type": "ConfigTimeProtectAction",
        "type": "TIME_PROTECT",
        "delayTime": 0.0,
        "aliasList": [
          ""
        ],
        "duration": 1.0,
        "checkNextImmediately": false,
        "protectTime": 1.0
      },
      {
        "$type": "ConfigSimpleBlackScreenAction",
        "type": "SIMPLE_BLACK_SCREEN",
        "delayTime": 0.0,
        "aliasList": [
          ""
        ],
        "duration": -1.0,
        "checkNextImmediately": false,
        "durationToBlack": 0.5,
        "durationKeepBlack": 1.0,
        "durationFromBlack": 0.5,
        "textMapID": ""
      },
      {
        "$type": "ConfigVisibleInterAction",
        "type": "VISIBLE",
        "delayTime": 0.5,
        "aliasList": [
          "10204"
        ],
        "duration": -1.0,
        "checkNextImmediately": false,
        "isVisible": false
      }
    ],
    [
      {
        "$type": "ConfigLookAtInterAction",
        "type": "LOOK_AT",
        "delayTime": 0.0,
        "aliasList": [
          "Avatar"
        ],
        "duration": -1.0,
        "checkNextImmediately": false,
        "enableHead": false,
        "useTargetPos": false,
        "targetOffset": {
          "x": 0.0,
          "y": 0.0,
          "z": 0.0
        },
        "targetPosition": {
          "x": 0.0,
          "y": 0.0,
          "z": 0.0
        },
        "headRotateVec": {
          "x": 0.0,
          "y": 0.0,
          "z": 0.0
        },
        "headTurnTime": 0.0,
        "enableBody": false,
        "bodyAngle": 0.0,
        "bodyTurnTime": 0.0
      },
      {
        "$type": "ConfigLookAtInterAction",
        "type": "LOOK_AT",
        "delayTime": 0.0,
        "aliasList": [
          "1005"
        ],
        "duration": -1.0,
        "checkNextImmediately": false,
        "enableHead": false,
        "useTargetPos": false,
        "targetOffset": {
          "x": 0.0,
          "y": 0.0,
          "z": 0.0
        },
        "targetPosition": {
          "x": 0.0,
          "y": 0.0,
          "z": 0.0
        },
        "headRotateVec": {
          "x": 0.0,
          "y": 0.0,
          "z": 0.0
        },
        "headTurnTime": 0.0,
        "enableBody": false,
        "bodyAngle": 0.0,
        "bodyTurnTime": 0.0
      },
      {
        "$type": "ConfigLookAtInterAction",
        "type": "LOOK_AT",
        "delayTime": 0.0,
        "aliasList": [
          "10204"
        ],
        "duration": -1.0,
        "checkNextImmediately": false,
        "enableHead": false,
        "useTargetPos": false,
        "targetOffset": {
          "x": 0.0,
          "y": 0.0,
          "z": 0.0
        },
        "targetPosition": {
          "x": 0.0,
          "y": 0.0,
          "z": 0.0
        },
        "headRotateVec": {
          "x": 0.0,
          "y": 0.0,
          "z": 0.0
        },
        "headTurnTime": 0.0,
        "enableBody": false,
        "bodyAngle": 0.0,
        "bodyTurnTime": 0.0
      }
    ]
  ],
  "actors": [
    {
      "configID": 0,
      "alias": "Avatar",
      "visible": true,
      "bornPointName": "Q40003Player"
    },
    {
      "configID": 1005,
      "alias": "1005",
      "visible": true,
      "bornPointName": "Q40003Paimon",
      "useRelativePos": false,
      "relativePos": {
        "x": 0.5,
        "y": 0.0,
        "z": 0.5
      },
      "relativeRot": {
        "x": 0.0,
        "y": 0.0,
        "z": 0.0
      }
    },
    {
      "configID": 10204,
      "alias": "10204",
      "visible": true,
      "bornPointName": "Q40003Xiao",
      "useRelativePos": false,
      "relativePos": {
        "x": 0.0,
        "y": 0.0,
        "z": 0.0
      },
      "relativeRot": {
        "x": 0.0,
        "y": 0.0,
        "z": 0.0
      }
    }
  ],
  "groupId": [
    {
      "index": 0,
      "grpId": 512683900,
      "nextGrpId": 512683901
    },
    {
      "index": 1,
      "grpId": 512683901,
      "nextGrpId": 512683902
    },
    {
      "index": 2,
      "grpId": 512683902,
      "nextGrpId": 512683903
    },
    {
      "index": 3,
      "grpId": 512683903,
      "nextGrpId": 512683904
    },
    {
      "index": 4,
      "grpId": 512683904,
      "nextGrpId": 512683905
    },
    {
      "index": 5,
      "grpId": 512683905,
      "nextGrpId": 512683906
    },
    {
      "index": 6,
      "grpId": 512683906,
      "nextGrpId": 512683907
    },
    {
      "index": 7,
      "grpId": 512683907,
      "nextGrpId": 512683908
    },
    {
      "index": 8,
      "grpId": 512683908,
      "nextGrpId": 3008299060
    },
    {
      "index": 9,
      "grpId": 3008299060,
      "nextGrpId": 3008299061
    },
    {
      "index": 10,
      "grpId": 3008299061,
      "nextGrpId": 3008299062
    },
    {
      "index": 11,
      "grpId": 3008299062,
      "nextGrpId": 3008299063
    },
    {
      "index": 12,
      "grpId": 3008299063,
      "nextGrpId": 3008299064
    },
    {
      "index": 13,
      "grpId": 3008299064,
      "nextGrpId": 3008299065
    },
    {
      "index": 14,
      "grpId": 3008299065,
      "nextGrpId": 3008299066
    },
    {
      "index": 15,
      "grpId": 3008299066,
      "nextGrpId": 3008299067
    },
    {
      "index": 16,
      "grpId": 3008299067,
      "nextGrpId": 3008299068
    },
    {
      "index": 17,
      "grpId": 3008299068,
      "nextGrpId": 3008299069
    },
    {
      "index": 18,
      "grpId": 3008299069,
      "nextGrpId": 3008299091
    },
    {
      "index": 19,
      "grpId": 3008299091,
      "nextGrpId": 3008299092
    },
    {
      "index": 20,
      "grpId": 3008299092,
      "nextGrpId": 3008299093
    },
    {
      "index": 21,
      "grpId": 3008299093,
      "nextGrpId": 3008299094
    },
    {
      "index": 22,
      "grpId": 3008299094,
      "nextGrpId": 3008299095
    },
    {
      "index": 23,
      "grpId": 3008299095,
      "nextGrpId": 3008299096
    },
    {
      "index": 24,
      "grpId": 3008299096,
      "nextGrpId": 3008299097
    },
    {
      "index": 25,
      "grpId": 3008299097,
      "nextGrpId": 3008299098
    },
    {
      "index": 26,
      "grpId": 3008299098,
      "nextGrpId": 3008299099
    },
    {
      "index": 27,
      "grpId": 3008299099,
      "nextGrpId": 3008299100
    },
    {
      "index": 28,
      "grpId": 3008299100,
      "nextGrpId": 3008299122
    },
    {
      "index": 29,
      "grpId": 3008299122,
      "nextGrpId": 3008299123
    }
  ]
}