{
  "talkId": 2003102,
  "dialogList": [
    {
      "id": 200310201,
      "nextDialogs": [
        200310202
      ],
      "talkRole": {
        "id": "1512",
        "type": "TALK_ROLE_NPC"
      },
      "talkContent": 2863311625
    },
    {
      "id": 200310202,
      "nextDialogs": [
        200310203
      ],
      "talkRole": {
        "id": "1512",
        "type": "TALK_ROLE_NPC"
      },
      "talkContent": 494561449
    },
    {
      "id": 200310203,
      "talkRole": {
        "id": "1512",
        "type": "TALK_ROLE_NPC"
      },
      "talkContent": 3020662241
    }
  ]
}