{
  "talkId": 20054021,
  "dialogList": [
    {
      "id": 2005402101,
      "nextDialogs": [
        2005402102
      ],
      "talkRole": {
        "id": "1441",
        "type": "TALK_ROLE_NPC"
      },
      "talkContent": 3125132313
    },
    {
      "id": 2005402102,
      "nextDialogs": [
        2005402103
      ],
      "talkRole": {
        "id": "1441",
        "type": "TALK_ROLE_NPC"
      },
      "talkContent": 1352598617
    },
    {
      "id": 2005402103,
      "nextDialogs": [
        2005402104
      ],
      "talkRole": {
        "id": "1441",
        "type": "TALK_ROLE_NPC"
      },
      "talkContent": 1164142001
    },
    {
      "id": 2005402104,
      "nextDialogs": [
        2005402105
      ],
      "talkRole": {
        "id": "1441",
        "type": "TALK_ROLE_NPC"
      },
      "talkContent": 3195099257
    },
    {
      "id": 2005402105,
      "nextDialogs": [
        2005402106
      ],
      "talkRole": {
        "id": "1441",
        "type": "TALK_ROLE_NPC"
      },
      "talkContent": 3669398585
    },
    {
      "id": 2005402106,
      "talkRole": {
        "id": "1441",
        "type": "TALK_ROLE_NPC"
      },
      "talkContent": 782012361
    }
  ]
}