{
  "talkId": 20054141,
  "dialogList": [
    {
      "id": 2005414101,
      "nextDialogs": [
        2005414102
      ],
      "talkRole": {
        "id": "1441",
        "type": "TALK_ROLE_NPC"
      },
      "talkContent": 1708541129
    },
    {
      "id": 2005414102,
      "nextDialogs": [
        2005414103
      ],
      "talkShowType": "TALK_SHOW_FORCE_SELECT",
      "talkRole": {
        "id": "",
        "type": "TALK_ROLE_PLAYER"
      },
      "talkContent": 2193307521,
      "optionIcon": "UI_Icon_Intee_DailyEvent_1"
    },
    {
      "id": 2005414103,
      "nextDialogs": [
        2005414104
      ],
      "talkRole": {
        "id": "1441",
        "type": "TALK_ROLE_NPC"
      },
      "talkContent": 1807119353
    },
    {
      "id": 2005414104,
      "nextDialogs": [
        2005414105
      ],
      "talkRole": {
        "id": "1441",
        "type": "TALK_ROLE_NPC"
      },
      "talkContent": 2863340953
    },
    {
      "id": 2005414105,
      "nextDialogs": [
        2005414106
      ],
      "talkRole": {
        "id": "1441",
        "type": "TALK_ROLE_NPC"
      },
      "talkContent": 1635912201
    },
    {
      "id": 2005414106,
      "nextDialogs": [
        2005414107
      ],
      "talkRole": {
        "id": "1441",
        "type": "TALK_ROLE_NPC"
      },
      "talkContent": 3016999233
    },
    {
      "id": 2005414107,
      "talkRole": {
        "id": "1441",
        "type": "TALK_ROLE_NPC"
      },
      "talkContent": 2656335121
    }
  ]
}