{
  "talkId": 2010106,
  "dialogList": [
    {
      "id": 201010601,
      "nextDialogs": [
        2010106021
      ],
      "talkShowType": "TALK_SHOW_FORCE_SELECT",
      "talkRole": {
        "id": "",
        "type": "TALK_ROLE_PLAYER"
      },
      "talkContent": 838411731
    },
    {
      "id": 2010106021,
      "nextDialogs": [
        201010602
      ],
      "talkRole": {
        "id": "1503",
        "type": "TALK_ROLE_NPC"
      },
      "talkContent": 2878628195
    },
    {
      "id": 201010602,
      "nextDialogs": [
        201010603,
        201010605
      ],
      "talkRole": {
        "id": "1503",
        "type": "TALK_ROLE_NPC"
      },
      "talkContent": 3375095467,
      "actionWhile": "TEST/Lua_20101_1"
    },
    {
      "id": 201010603,
      "nextDialogs": [
        201010604
      ],
      "talkRole": {
        "id": "",
        "type": "TALK_ROLE_PLAYER"
      },
      "talkContent": 2799877059
    },
    {
      "id": 201010604,
      "nextDialogs": [
        201010609
      ],
      "talkRole": {
        "id": "1503",
        "type": "TALK_ROLE_NPC"
      },
      "talkContent": 3264747987,
      "actionWhile": "TEST/Lua_20101_1B"
    },
    {
      "id": 201010609,
      "nextDialogs": [
        201010610,
        201010612,
        201010614
      ],
      "talkRole": {
        "id": "1503",
        "type": "TALK_ROLE_NPC"
      },
      "talkContent": 3191732579
    },
    {
      "id": 201010610,
      "nextDialogs": [
        201010611
      ],
      "talkRole": {
        "id": "",
        "type": "TALK_ROLE_PLAYER"
      },
      "talkContent": 3557670987
    },
    {
      "id": 201010611,
      "nextDialogs": [
        201010616
      ],
      "talkRole": {
        "id": "1503",
        "type": "TALK_ROLE_NPC"
      },
      "talkContent": 611275595,
      "actionWhile": "TEST/Lua_20101_1A"
    },
    {
      "id": 201010616,
      "talkRole": {
        "id": "1503",
        "type": "TALK_ROLE_NPC"
      },
      "talkContent": 2520791115,
      "actionWhile": "TEST/Lua_20101_1X"
    },
    {
      "id": 201010612,
      "nextDialogs": [
        201010613
      ],
      "talkRole": {
        "id": "",
        "type": "TALK_ROLE_PLAYER"
      },
      "talkContent": 799253019
    },
    {
      "id": 201010613,
      "nextDialogs": [
        201010616
      ],
      "talkRole": {
        "id": "1503",
        "type": "TALK_ROLE_NPC"
      },
      "talkContent": 2579789715,
      "actionWhile": "TEST/Lua_20101_1B"
    },
    {
      "id": 201010614,
      "nextDialogs": [
        201010615
      ],
      "talkRole": {
        "id": "",
        "type": "TALK_ROLE_PLAYER"
      },
      "talkContent": 2770903731
    },
    {
      "id": 201010615,
      "nextDialogs": [
        201010616
      ],
      "talkRole": {
        "id": "1503",
        "type": "TALK_ROLE_NPC"
      },
      "talkContent": 414613923,
      "actionWhile": "TEST/Lua_20101_1C"
    },
    {
      "id": 201010605,
      "nextDialogs": [
        201010606
      ],
      "talkRole": {
        "id": "",
        "type": "TALK_ROLE_PLAYER"
      },
      "talkContent": 2819857011
    },
    {
      "id": 201010606,
      "nextDialogs": [
        201010609
      ],
      "talkRole": {
        "id": "1503",
        "type": "TALK_ROLE_NPC"
      },
      "talkContent": 2735056851,
      "actionWhile": "TEST/Lua_20101_1A"
    }
  ]
}