{
  "talkId": 34908,
  "type": "FREE",
  "dialogList": [
    {
      "id": 3490801,
      "nextDialogs": [
        3490803
      ],
      "talkRole": {
        "id": "1244",
        "type": "TALK_ROLE_NPC"
      },
      "talkContent": 2813884307,
      "talkRoleName": 2528736972,
      "actionBefore": "TEST/Readable01"
    },
    {
      "id": 3490803,
      "nextDialogs": [
        3490804
      ],
      "talkRole": {
        "id": "1244",
        "type": "TALK_ROLE_NPC"
      },
      "talkContent": 2136855923,
      "talkRoleName": 1616177804
    },
    {
      "id": 3490804,
      "talkRole": {
        "id": "1244",
        "type": "TALK_ROLE_NPC"
      },
      "talkContent": 781686075,
      "talkRoleName": 1566562196
    }
  ]
}