{
  "sceneId": 3,
  "polygons": [
    {
      "localPolygonId": 300700001,
      "yMax": 280.0,
      "yMin": 250.0,
      "vertices": [
        {
          "x": 2427.08716,
          "y": 263.7196,
          "z": 355.561249
        },
        {
          "x": 2430.0332,
          "y": 263.855652,
          "z": 366.7637
        },
        {
          "x": 2438.468,
          "y": 266.250977,
          "z": 386.09198
        },
        {
          "x": 2446.978,
          "y": 263.230042,
          "z": 389.5911
        },
        {
          "x": 2459.59448,
          "y": 262.800476,
          "z": 384.089081
        },
        {
          "x": 2468.49146,
          "y": 262.456451,
          "z": 375.267883
        },
        {
          "x": 2472.30273,
          "y": 262.226685,
          "z": 364.691376
        },
        {
          "x": 2469.47485,
          "y": 262.383057,
          "z": 350.45694
        },
        {
          "x": 2463.97583,
          "y": 262.75824,
          "z": 337.325684
        },
        {
          "x": 2454.03052,
          "y": 263.291748,
          "z": 334.521057
        },
        {
          "x": 2445.30029,
          "y": 262.576538,
          "z": 338.1931
        },
        {
          "x": 2434.636,
          "y": 262.8838,
          "z": 344.8366
        }
      ],
      "tags": []
    }
  ]
}